{"name":"navigateToSignOnPage","id":"com.jpetstore.tests.Sample:navigateToSignOnPage","testCaseName":"com.jpetstore.tests.Sample","testSteps":[{"number":1,"description":"Navigating to Login Page","duration":8487,"startTime":"2021-01-03T18:23:53.957464300Z[Europe/London]","screenshots":[{"screenshot":"98c6de9f6fb0648aab10acd8fb838193cfc71d9f754c6e39f05c9b30e8d7672f.png","timeStamp":1609698241930},{"screenshot":"d8ed1865d21835f19df4b09c0716225e05387a418e94a7fbe1c2e5a86bd2b9f5.png","timeStamp":1609698242442},{"screenshot":"d8ed1865d21835f19df4b09c0716225e05387a418e94a7fbe1c2e5a86bd2b9f5.png","timeStamp":1609698242445}],"result":"SUCCESS","precondition":false,"level":0}],"userStory":{"id":"com.jpetstore.tests.Sample","storyName":"Sample","storyClassName":"com.jpetstore.tests.Sample","path":"com.jpetstore.tests","type":"story"},"featureTag":{"name":"Tests/Sample","type":"story","displayName":"Tests/Sample"},"title":"Navigating to the signout page","tags":[{"name":"Tests/Sample","type":"story","displayName":"Tests/Sample"}],"startTime":"2021-01-03T18:23:53.882439600Z[Europe/London]","duration":8564,"projectKey":"","sessionId":"ccf0ab56cdfca3f5f443fdfa93475b20","driver":"chrome","isManualTestingUpToDate":false,"manual":false,"testSource":"JUnit","result":"SUCCESS"}